sam2pairview
